{"RECORDS":[{"picId":15,"width":1920,"height":1080,"imgSrc":"http://localhost:3000/imgs/ed009ad907b1350f4658c3804.jpg","title":"乐飞","picState":1,"isTop":0,"time":1654866080818,"userId":1,"account":"admin"},{"picId":29,"width":1920,"height":1080,"imgSrc":"http://localhost:3000/imgs/f4dd625b717b0e5cef1dcde03.jpg","title":"123456","picState":1,"isTop":0,"time":1655975254224,"userId":1,"account":"admin"},{"picId":11,"width":1920,"height":1080,"imgSrc":"http://localhost:3000/imgs/ed009ad907b1350f4658c3800.png","title":"日落","picState":2,"isTop":0,"time":1655794954604,"userId":1,"account":"admin"},{"picId":8,"width":1920,"height":1080,"imgSrc":"http://localhost:3000/imgs/e5065cc8d903a5eec3c754900.jpg","title":"七里香","picState":1,"isTop":0,"time":1654514185896,"userId":1,"account":"admin"},{"picId":7,"width":1920,"height":1080,"imgSrc":"http://localhost:3000/imgs/6b90fc156dcf1a99576d9a502.jpg","title":"11","picState":2,"isTop":0,"time":1654514121916,"userId":1,"account":"admin"},{"picId":5,"width":1920,"height":1160,"imgSrc":"http://localhost:3000/imgs/6b90fc156dcf1a99576d9a500.jpg","title":"天空","picState":1,"isTop":0,"time":1655976299133,"userId":1,"account":"admin"},{"picId":25,"width":1920,"height":1080,"imgSrc":"http://localhost:3000/imgs/93626a907dbec51892ea5e900.jpg","title":"大白","picState":1,"isTop":0,"time":1656144091838,"userId":1,"account":"admin"},{"picId":23,"width":550,"height":307,"imgSrc":"http://localhost:3000/imgs/28bc23285db7252bf89791a03.jpg","title":"科比","picState":2,"isTop":0,"time":1655794958338,"userId":1,"account":"admin"},{"picId":23,"width":550,"height":307,"imgSrc":"http://localhost:3000/imgs/28bc23285db7252bf89791a03.jpg","title":"科比","picState":1,"isTop":0,"time":1654513876005,"userId":2,"account":"user"},{"picId":24,"width":1200,"height":800,"imgSrc":"http://localhost:3000/imgs/578d0e3f371508153da154b00.jpeg","title":"袋鼠","picState":1,"isTop":0,"time":1655976435622,"userId":"1"},{"picId":25,"width":1900,"height":1229,"imgSrc":"http://localhost:3000/imgs/302483cc44fb0f848b2f57100.jpeg","title":"天空","picState":0,"isTop":1,"time":1655712560446,"userId":"1","account":"admin"},{"picId":26,"width":1200,"height":900,"imgSrc":"http://localhost:3000/imgs/a5697d9ed02272b75bb1b5800.jpeg","title":"小狗","picState":1,"isTop":1,"time":1655779577116,"userId":"1"},{"picId":27,"width":1200,"height":675,"imgSrc":"http://localhost:3000/imgs/f73e84fb6be90564e7b8b6d00.jpeg","title":"海洋","picState":0,"isTop":1,"time":1655783016183,"userId":"1","account":"admin"},{"picId":29,"width":4878,"height":3252,"imgSrc":"http://localhost:3000/imgs/2b120cc80616f47f5970a4e00.jpeg","title":"红色的云朵","picState":0,"isTop":1,"time":1655783691881,"userId":"1","account":"admin"},{"picId":30,"width":1200,"height":675,"imgSrc":"http://localhost:3000/imgs/72cf19bd323958fb5e4895900.jpeg","title":"绿色的","picState":2,"isTop":0,"time":1656140753345,"userId":"1","account":"admin"},{"picId":31,"width":1200,"height":799,"imgSrc":"http://localhost:3000/imgs/72cf19bd323958fb5e4895901.jpeg","title":"老虎","picState":1,"isTop":0,"time":1655976431875,"userId":"1","account":"admin"},{"picId":32,"width":1200,"height":600,"imgSrc":"http://localhost:3000/imgs/72cf19bd323958fb5e4895902.jpeg","title":"白玫瑰","picState":1,"isTop":0,"time":1656140997376,"userId":"2","account":"user"},{"picId":33,"width":1200,"height":675,"imgSrc":"http://localhost:3000/imgs/72cf19bd323958fb5e4895903.jpeg","title":"雪山","picState":2,"isTop":0,"time":1655976436985,"userId":"2","account":"user"}]}